mdfy_esa/__init__.py
mdfy_esa/mdfy_esa.py
mdfy_esa/py.typed
mdfy_esa-0.5.0.dist-info/LICENSE
mdfy_esa-0.5.0.dist-info/METADATA
mdfy_esa-0.5.0.dist-info/WHEEL
mdfy_esa-0.5.0.dist-info/RECORD
