Metadata-Version: 2.1
Name: mdfy-esa
Version: 0.5.0
Summary: mdfy plugin for esa.
Home-page: https://github.com/argonism/mdfy-esa
License: MIT
Author: k-ush
Author-email: argoooooon@gmail.com
Requires-Python: >=3.8,<4.0
Classifier: License :: OSI Approved :: MIT License
Classifier: Programming Language :: Python :: 3
Classifier: Programming Language :: Python :: 3.8
Classifier: Programming Language :: Python :: 3.9
Classifier: Programming Language :: Python :: 3.10
Classifier: Programming Language :: Python :: 3.11
Classifier: Typing :: Typed
Requires-Dist: mdfy (>=0.3.0,<0.4.0)
Requires-Dist: piyo (>=1.1.1,<2.0.0)
Requires-Dist: tox-gh-actions (>=3.1.3,<4.0.0)
Project-URL: Repository, https://github.com/argonism/mdfy-esa
